textscout/__init__.py
textscout/analyzer.py
textscout-0.2.0.dist-info/METADATA
textscout-0.2.0.dist-info/WHEEL
textscout-0.2.0.dist-info/RECORD
